DDoS.py
portinousDos-1.5.dist-info/METADATA
portinousDos-1.5.dist-info/WHEEL
portinousDos-1.5.dist-info/top_level.txt
portinousDos-1.5.dist-info/RECORD
