Metadata-Version: 2.1
Name: portinousDos
Version: 1.5
Summary: stress testing on python
Home-page: UNKNOWN
Author: UNKNOWN
Author-email: UNKNOWN
License: UNKNOWN
Platform: UNKNOWN
